share/pestfile.tpl
tsblender/__init__.py
tsblender/tsblender.py
tsblender/get_series/get_series_csv.py
tsblender/get_series/get_series_gsflow_gage.py
tsblender/get_series/get_series_hspfbin.py
tsblender/get_series/get_series_plotgen.py
tsblender/get_series/get_series_ssf.py
tsblender/get_series/get_series_statvar.py
tsblender/get_series/get_series_tetrad.py
tsblender/get_series/get_series_ufore_hydro.py
tsblender/get_series/get_series_wdm.py
tsblender/get_series/get_series_xlsx.py
tsblender/series/series_base_level.py
tsblender/series/series_clean.py
tsblender/series/series_compare.py
tsblender/series/series_difference.py
tsblender/series/series_displace.py
tsblender/series/series_equation.py
tsblender/series/series_statistics.py
tsblender/toolbox_utils/docs/conf.py
tsblender/toolbox_utils/src/toolbox_utils/__init__.py
tsblender/toolbox_utils/src/toolbox_utils/tsutils.py
tsblender/toolbox_utils/src/toolbox_utils/readers/__init__.py
tsblender/toolbox_utils/src/toolbox_utils/readers/hbn.py
tsblender/toolbox_utils/src/toolbox_utils/readers/plotgen.py
tsblender/toolbox_utils/src/toolbox_utils/readers/wdm.py
tsblender/toolbox_utils/tests/test_asbestfreq.py
tsblender/toolbox_utils/tests/test_date_slice.py
tsblender/toolbox_utils/tests/test_dateparse.py
tsblender/toolbox_utils/tests/test_extract.py
tsblender/toolbox_utils/tests/test_hbn.py
tsblender/toolbox_utils/tests/test_make_list.py
tsblender/toolbox_utils/tests/test_period_timestamp.py
tsblender/toolbox_utils/tests/test_plotgen.py
tsblender/toolbox_utils/tests/test_range_to_numlist.py
tsblender/toolbox_utils/tests/test_read.py
tsblender/toolbox_utils/tests/test_wdm.py
tsblender-103.3.0.dist-info/licenses/LICENSE.txt
tsblender-103.3.0.dist-info/METADATA
tsblender-103.3.0.dist-info/WHEEL
tsblender-103.3.0.dist-info/entry_points.txt
tsblender-103.3.0.dist-info/top_level.txt
tsblender-103.3.0.dist-info/RECORD
