Metadata-Version: 2.4
Name: tsblender
Version: 103.3.0
Summary: Drop-in replacement for TSPROC that is a utility for inverse modeling with PEST.
Author-email: Tim Cera <tim@cerazone.net>
License: BSD-3-Clause
Project-URL: documentation, https://timcera.bitbucket.io/tsblender/docs/index.html#tsblender-documentation
Project-URL: github, https://github.com/timcera/tsblender
Project-URL: bitbucket, https://bitbucket.org/timcera/tsblender/src/main/
Keywords: baseflow,cli-app,hydrology,parameter-estimation,python,time-series,tsproc
Classifier: Development Status :: 5 - Production/Stable
Classifier: Environment :: Console
Classifier: Intended Audience :: Developers
Classifier: Intended Audience :: End Users/Desktop
Classifier: Intended Audience :: Science/Research
Classifier: License :: OSI Approved :: BSD License
Classifier: Natural Language :: English
Classifier: Operating System :: OS Independent
Classifier: Programming Language :: Python :: 3.9
Classifier: Programming Language :: Python :: 3.10
Classifier: Programming Language :: Python :: 3.11
Classifier: Programming Language :: Python :: 3.12
Classifier: Programming Language :: Python :: 3.13
Classifier: Programming Language :: Python :: 3 :: Only
Classifier: Topic :: Scientific/Engineering
Classifier: Topic :: Scientific/Engineering :: Information Analysis
Classifier: Topic :: Software Development :: Libraries :: Python Modules
Requires-Python: >=3.9
License-File: LICENSE.txt
Requires-Dist: cltoolbox>=1.0.0
Requires-Dist: dateparser
Requires-Dist: flopy
Requires-Dist: fortranformat
Requires-Dist: hspf_reader
Requires-Dist: hydrotoolbox>=2.0.12
Requires-Dist: numpy<2.0; python_version == "3.9"
Requires-Dist: pandas[excel]
Requires-Dist: pint!=0.21.*
Requires-Dist: pint-pandas
Requires-Dist: pydantic
Requires-Dist: pyemu
Requires-Dist: python-dateutil
Requires-Dist: tstoolbox>=106.0.0
Requires-Dist: xlsxwriter
Dynamic: license-file
